hpconfig/__init__.py
hpconfig-0.0.0.dist-info/LICENSE
hpconfig-0.0.0.dist-info/METADATA
hpconfig-0.0.0.dist-info/WHEEL
hpconfig-0.0.0.dist-info/top_level.txt
hpconfig-0.0.0.dist-info/RECORD
